tvoozkothxxx001/__init__.py
tvoozkothxxx001/setup.py
tvoozkothxxx001-1234567890.0.0.dist-info/METADATA
tvoozkothxxx001-1234567890.0.0.dist-info/WHEEL
tvoozkothxxx001-1234567890.0.0.dist-info/top_level.txt
tvoozkothxxx001-1234567890.0.0.dist-info/RECORD
