Metadata-Version: 2.1
Name: tvoozkothxxx001
Version: 1234567890.0.0
Summary: tvoozkothxxx001: Controller Script for tvoozkothxxx001
Home-page: https://github.com/TvoozMagnificent/tvoozkothxxx001
Author: TvoozMagnificent
Author-email: luchang1106@icloud.com
License: MIT
Platform: UNKNOWN
Classifier: License :: OSI Approved :: MIT License
Classifier: Programming Language :: Python :: 3
Requires-Dist: funcopy
Requires-Dist: rich
